word_reaper/__init__.py
word_reaper/word_reaper.py
word_reaper/bin/combinator.bin
word_reaper/bin/mp32.bin
word_reaper/bin/mp64.bin
word_reaper/bin/permute.bin
word_reaper/rules/Incisive-leetspeak.rule
word_reaper/rules/InsidePro-HashManager.rule
word_reaper/rules/InsidePro-PasswordsPro.rule
word_reaper/rules/OneRuleToRuleThemAll.rule
word_reaper/rules/OneRuleToRuleThemStill.rule
word_reaper/rules/T0XlC-insert_00-99_1950-2050_toprules_0_F.rule
word_reaper/rules/T0XlC-insert_space_and_special_0_F.rule
word_reaper/rules/T0XlC-insert_top_100_passwords_1_G.rule
word_reaper/rules/T0XlC.rule
word_reaper/rules/T0XlC_3_rule.rule
word_reaper/rules/T0XlC_insert_HTML_entities_0_Z.rule
word_reaper/rules/T0XlCv2.rule
word_reaper/rules/best66.rule
word_reaper/rules/combinator.rule
word_reaper/rules/d3ad0ne.rule
word_reaper/rules/d3adhob0.rule
word_reaper/rules/dive.rule
word_reaper/rules/generated.rule
word_reaper/rules/generated2.rule
word_reaper/rules/leetspeak.rule
word_reaper/rules/oscommerce.rule
word_reaper/rules/rockyou-30000.rule
word_reaper/rules/specific.rule
word_reaper/rules/stacking58.rule
word_reaper/rules/toggles1.rule
word_reaper/rules/toggles2.rule
word_reaper/rules/toggles3.rule
word_reaper/rules/toggles4.rule
word_reaper/rules/toggles5.rule
word_reaper/rules/top10_2025.rule
word_reaper/rules/unix-ninja-leetspeak.rule
word_reaper/rules/zombiecrack_leet.rule
word_reaper/scraper/__init__.py
word_reaper/scraper/file_loader.py
word_reaper/scraper/github_scraper.py
word_reaper/scraper/html_scraper.py
word_reaper/scraper/text_scraper.py
word_reaper/utils/__init__.py
word_reaper/utils/ascii.py
word_reaper/utils/ascii_art.py
word_reaper/utils/cleaner.py
word_reaper/utils/combinator.py
word_reaper/utils/combinator_hashcat.py
word_reaper/utils/formatter.py
word_reaper/utils/hashcat_utils.py
word_reaper/utils/merge.py
word_reaper/utils/permutator.py
word_reaper/utils/progress_reporting.py
word_reaper/utils/rule_generator.py
word_reaper/utils/selective_leet.py
word_reaper-2.0.0.dist-info/licenses/LICENSE
word_reaper-2.0.0.dist-info/METADATA
word_reaper-2.0.0.dist-info/WHEEL
word_reaper-2.0.0.dist-info/entry_points.txt
word_reaper-2.0.0.dist-info/top_level.txt
word_reaper-2.0.0.dist-info/RECORD
