Metadata-Version: 2.4
Name: word-reaper
Version: 2.0.0
Summary: Reap & Forge Wordlists for Password Cracking
Home-page: https://github.com/Nemorous/wordreaper
Author: d4rkfl4m3z
License: MIT
Project-URL: Documentation, https://github.com/Nemorous/wordreaper#readme
Project-URL: Bug Tracker, https://github.com/Nemorous/wordreaper/issues
Project-URL: Source, https://github.com/Nemorous/wordreaper
Classifier: Development Status :: 3 - Alpha
Classifier: Intended Audience :: Developers
Classifier: Intended Audience :: Information Technology
Classifier: License :: OSI Approved :: MIT License
Classifier: Programming Language :: Python :: 3
Classifier: Programming Language :: Python :: 3.6
Classifier: Programming Language :: Python :: 3.7
Classifier: Programming Language :: Python :: 3.8
Classifier: Programming Language :: Python :: 3.9
Classifier: Operating System :: OS Independent
Classifier: Topic :: Security
Classifier: Topic :: Utilities
Requires-Python: >=3.6
License-File: LICENSE
Requires-Dist: requests
Requires-Dist: beautifulsoup4
Requires-Dist: colorama
Requires-Dist: tqdm
Requires-Dist: psutil
Requires-Dist: wordninja
Provides-Extra: optimizations
Requires-Dist: psutil; extra == "optimizations"
Dynamic: author
Dynamic: classifier
Dynamic: description
Dynamic: description-content-type
Dynamic: home-page
Dynamic: license
Dynamic: license-file
Dynamic: project-url
Dynamic: provides-extra
Dynamic: requires-dist
Dynamic: requires-python
Dynamic: summary
